<?xml version="1.0" encoding="UTF-8"?>
<objects serializationModel="Studio.02.03.00">
	<object class="AudioFile" id="{9e4d8dee-979c-4e0a-9b1b-bb3b361aa084}">
		<property name="assetPath">
			<value>SFX/SD Sfx/sfx_radio_static_lp.wav</value>
		</property>
		<property name="isStreaming">
			<value>true</value>
		</property>
		<property name="frequencyInKHz">
			<value>48</value>
		</property>
		<property name="channelCount">
			<value>1</value>
		</property>
		<property name="length">
			<value>29.588395833333333</value>
		</property>
		<relationship name="masterAssetFolder">
			<destination>{0007398a-8526-4222-84a0-9fc057cc09e5}</destination>
		</relationship>
	</object>
</objects>
